batch_audio_extract/__init__.py
batch_audio_extract/ffmpeg.py
batch_audio_extract/gui.py
batch_audio_extract/main.py
batch_audio_extract/process.py
batch_audio_extract/welcome.py
batch_audio_extract-0.6.0.dist-info/METADATA
batch_audio_extract-0.6.0.dist-info/WHEEL
batch_audio_extract-0.6.0.dist-info/entry_points.txt
batch_audio_extract-0.6.0.dist-info/RECORD
