Metadata-Version: 2.4
Name: batch_audio_extract
Version: 0.6.0
Summary: A mass treatment script for extracting part of audio files using FFMPEG
Project-URL: Homepage, https://github.com/makiwara-fr/audio_extract
Project-URL: Bug Tracker, https://github.com/makiwara-fr/audio_extract/issues
Author-email: makiwara-fr <makiwara@makiwara.com>
Classifier: License :: OSI Approved :: MIT License
Classifier: Operating System :: OS Independent
Classifier: Programming Language :: Python :: 3
Requires-Python: >=3.7
Requires-Dist: pyyaml
